Metadata-Version: 2.1
Name: emailz
Version: 0.12
Summary: easy use for send emails
Home-page: https://github.com/hanzhichao/emailz
Author: Han Zhichao
Author-email: superhin@126.com
License: MIT license
Keywords: emailz,email,attachments
Platform: UNKNOWN
Classifier: Programming Language :: Python
Classifier: Programming Language :: Python :: 2.7
Classifier: Programming Language :: Python :: 3.7
